ksvg_restyle/__init__.py
ksvg_restyle/__main__.py
ksvg_restyle/cli/__init__.py
ksvg_restyle/cli/cmd.py
ksvg_restyle/cli/env.py
ksvg_restyle/cli/handlers.py
ksvg_restyle/core/__init__.py
ksvg_restyle/core/builder.py
ksvg_restyle/core/parsers/__init__.py
ksvg_restyle/core/parsers/svg.py
ksvg_restyle/core/parsers/theme.py
ksvg_restyle/core/wrappers.py
ksvg_restyle/templates/stylesheet.jinja2
ksvg_restyle/templates/transform.xsl
ksvg_restyle-0.1.8.dist-info/LICENSE
ksvg_restyle-0.1.8.dist-info/METADATA
ksvg_restyle-0.1.8.dist-info/WHEEL
ksvg_restyle-0.1.8.dist-info/entry_points.txt
ksvg_restyle-0.1.8.dist-info/RECORD
