Metadata-Version: 2.3
Name: ksvg_restyle
Version: 0.1.8
Summary: A CLI tool to apply Plasma Color Schemes to SVG widgets
License: LGPL-2.1-or-later
Keywords: cli,kde,svg,color,widget,theme,plasma
Author: oniko94
Author-email: onikolaiev94@outlook.com
Maintainer: oniko94
Maintainer-email: onikolaiev94@outlook.com
Requires-Python: >=3.12,<4.0
Classifier: License :: OSI Approved
Classifier: Programming Language :: Python :: 3
Classifier: Programming Language :: Python :: 3.12
Classifier: Programming Language :: Python :: 3.13
Requires-Dist: click (>=8.1.8,<9.0.0)
Requires-Dist: jinja2 (>=3.1.5,<4.0.0)
Requires-Dist: lxml (>=5.3.0,<6.0.0)
Project-URL: Repository, https://github.com/squalorware/KSVG_Restyle
